dyna_gsm_module/db_lib.py
dyna_gsm_module/gsm_modules.py
dyna_gsm_module/runner.py
dyna_gsm_module/sms_data.py
dyna_gsm_module-0.0.5.dist-info/DESCRIPTION.rst
dyna_gsm_module-0.0.5.dist-info/METADATA
dyna_gsm_module-0.0.5.dist-info/RECORD
dyna_gsm_module-0.0.5.dist-info/WHEEL
dyna_gsm_module-0.0.5.dist-info/entry_points.txt
dyna_gsm_module-0.0.5.dist-info/metadata.json
dyna_gsm_module-0.0.5.dist-info/top_level.txt
