Metadata-Version: 2.0
Name: dyna-gsm-module
Version: 0.0.5
Summary: GSM modules required for dynaslope 3 project
Home-page: https://github.com/jgeliberte/dyna-gsm-module
Author: John D. Geliberte
Author-email: gelibertejohn@gmail.com
License: MIT
Platform: UNKNOWN
Classifier: Programming Language :: Python :: 3.5
Classifier: License :: OSI Approved :: MIT License
Classifier: Operating System :: OS Independent
Requires-Dist: serial
Requires-Dist: RPi.GPIO
Requires-Dist: python-gsmmodem-new
Requires-Dist: configparser
